astro_senpai/__init__.py
astro_senpai-0.0.0.dist-info/METADATA
astro_senpai-0.0.0.dist-info/WHEEL
astro_senpai-0.0.0.dist-info/RECORD
